music_voicegen/__init__.py
music_voicegen/music_voicegen.py
music_voicegen-0.1.1.dist-info/licenses/LICENSE
music_voicegen-0.1.1.dist-info/METADATA
music_voicegen-0.1.1.dist-info/WHEEL
music_voicegen-0.1.1.dist-info/top_level.txt
music_voicegen-0.1.1.dist-info/RECORD
