Metadata-Version: 2.4
Name: music_voicegen
Version: 0.1.1
Summary: Musical MIDI voice generation
Author-email: Gene Boggs <gene.boggs@gmail.com>, Jeremy Mates <jmates@cpan.org>
License:                     GNU GENERAL PUBLIC LICENSE
Project-URL: Homepage, https://github.com/ology/python-music-voicegen
Project-URL: Repository, https://github.com/ology/python-music-voicegen.git
Project-URL: Issues, https://github.com/ology/python-music-voicegen/issues
Classifier: Development Status :: 2 - Pre-Alpha
Classifier: Programming Language :: Python
Classifier: Programming Language :: Python :: 3
Classifier: Programming Language :: Python :: 3.9
Classifier: Programming Language :: Python :: 3.10
Classifier: Programming Language :: Python :: 3.11
Classifier: Programming Language :: Python :: 3.12
Requires-Python: >=3.9
License-File: LICENSE
Dynamic: license-file
